tinyppl/__init__.py
tinyppl-0.0.0.dist-info/METADATA
tinyppl-0.0.0.dist-info/WHEEL
tinyppl-0.0.0.dist-info/top_level.txt
tinyppl-0.0.0.dist-info/RECORD
