Metadata-Version: 2.1
Name: tinyppl
Version: 0.0.0
Summary: Coming soon
Author-email: Sam Duffield <s@mduffield.com>
